__builtins__.pyi
_boot.pyi
_espnow.pyi
_onewire.pyi
apa102.pyi
binascii.pyi
btree.pyi
cryptolib.pyi
deflate.pyi
dht.pyi
ds18x20.pyi
errno.pyi
esp.pyi
espnow.pyi
flashbdev.pyi
framebuf.pyi
gc.pyi
hashlib.pyi
heapq.pyi
inisetup.pyi
lwip.pyi
machine.pyi
math.pyi
micropython.pyi
mip/__init__.pyi
neopixel.pyi
network.pyi
ntptime.pyi
onewire.pyi
platform.pyi
port_diag.pyi
random.pyi
requests/__init__.pyi
select.pyi
socket.pyi
ssd1306.pyi
time.pyi
tls.pyi
uarray.pyi
uasyncio.pyi
ubinascii.pyi
ubluetooth.pyi
ucryptolib.pyi
uerrno.pyi
uhashlib.pyi
uheapq.pyi
uio.pyi
ujson.pyi
umachine.pyi
uos.pyi
uplatform.pyi
urandom.pyi
ure.pyi
urequests.pyi
uselect.pyi
usocket.pyi
ussl.pyi
ustruct.pyi
usys.pyi
utime.pyi
uwebsocket.pyi
uzlib.pyi
webrepl.pyi
webrepl_setup.pyi
micropython_esp8266_esp8266_generic_stubs-1.27.0.post1.dist-info/LICENSE.md
micropython_esp8266_esp8266_generic_stubs-1.27.0.post1.dist-info/METADATA
micropython_esp8266_esp8266_generic_stubs-1.27.0.post1.dist-info/WHEEL
micropython_esp8266_esp8266_generic_stubs-1.27.0.post1.dist-info/RECORD
